partisan_dislocation/__init__.py
partisan_dislocation/partisan_dislocation.py
partisan_dislocation/tests/test_partisan_dislocation.py
partisan_dislocation-0.8.0.dist-info/LICENSE
partisan_dislocation-0.8.0.dist-info/WHEEL
partisan_dislocation-0.8.0.dist-info/METADATA
partisan_dislocation-0.8.0.dist-info/RECORD
