Metadata-Version: 2.1
Name: partisan_dislocation
Version: 0.8.0
Summary: Partisan Dislocation
Home-page: https://github.com/nickeubank/partisan_dislocation/
Author: Deford, Eubank, and Rodden
Author-email: nick@nickeubank.com
Requires-Python: >=3.7
Classifier: License :: OSI Approved :: MIT License
Classifier: Programming Language :: Python :: 3.6
Classifier: Programming Language :: Python :: 3.7
Classifier: Operating System :: OS Independent
Requires-Dist: scipy >= 1.3
Requires-Dist: geopandas >= 0.7
